mcserverapi/__init__.py
mcserverapi/parser.py
mcserverapi/si.py
mcserverapi-1.0.3.dist-info/METADATA
mcserverapi-1.0.3.dist-info/WHEEL
mcserverapi-1.0.3.dist-info/top_level.txt
mcserverapi-1.0.3.dist-info/RECORD
